multiai_tts/__init__.py
multiai_tts/prompt.py
multiai_tts-0.2.1.dist-info/METADATA
multiai_tts-0.2.1.dist-info/WHEEL
multiai_tts-0.2.1.dist-info/licenses/LICENSE
multiai_tts-0.2.1.dist-info/RECORD
