Metadata-Version: 2.4
Name: multiai-tts
Version: 0.2.1
Summary: TTS extension for multiai using OpenAI, Google GenAI and Azure Speech
Project-URL: Homepage, https://github.com/sekika/multiai-tts
Project-URL: Bug Tracker, https://github.com/sekika/multiai-tts/issues
Author: Katsutoshi Seki
License: MIT
License-File: LICENSE
Classifier: License :: OSI Approved :: MIT License
Classifier: Operating System :: OS Independent
Classifier: Programming Language :: Python :: 3
Requires-Python: >=3.8
Requires-Dist: azure-cognitiveservices-speech
Requires-Dist: google-genai
Requires-Dist: multiai
Requires-Dist: openai
Requires-Dist: pydub
Requires-Dist: sounddevice
Requires-Dist: soundfile
